ambientco2/__init__.py
ambientco2-0.0.1.dist-info/LICENSE
ambientco2-0.0.1.dist-info/METADATA
ambientco2-0.0.1.dist-info/WHEEL
ambientco2-0.0.1.dist-info/top_level.txt
ambientco2-0.0.1.dist-info/RECORD
