Metadata-Version: 2.1
Name: ambientco2
Version: 0.0.1
Summary: Python module for CozIR Ambient CO2 sensors
Home-page: https://github.com/mjackdk/PythonCO2
Author: Michael Jack
Author-email: mjpub@me.com
License: UNKNOWN
Platform: UNKNOWN
Classifier: Programming Language :: Python :: 3
Classifier: License :: OSI Approved :: MIT License
Classifier: Operating System :: OS Independent
Requires-Python: >=3.6
